zest/releaser/__init__.py
zest/releaser/addchangelogentry.py
zest/releaser/baserelease.py
zest/releaser/bumpversion.py
zest/releaser/choose.py
zest/releaser/fullrelease.py
zest/releaser/git.py
zest/releaser/lasttagdiff.py
zest/releaser/lasttaglog.py
zest/releaser/longtest.py
zest/releaser/postrelease.py
zest/releaser/preparedocs.py
zest/releaser/prerelease.py
zest/releaser/pypi.py
zest/releaser/release.py
zest/releaser/utils.py
zest/releaser/vcs.py
zest/releaser/tests/__init__.py
zest/releaser/tests/addchangelogentry.txt
zest/releaser/tests/baserelease.txt
zest/releaser/tests/bumpversion.txt
zest/releaser/tests/choose.txt
zest/releaser/tests/cmd_error.py
zest/releaser/tests/example.tar
zest/releaser/tests/fullrelease.txt
zest/releaser/tests/functional-git.txt
zest/releaser/tests/functional-with-hooks.txt
zest/releaser/tests/functional.py
zest/releaser/tests/git.txt
zest/releaser/tests/postrelease.txt
zest/releaser/tests/preparedocs.txt
zest/releaser/tests/prerelease.txt
zest/releaser/tests/pypi.txt
zest/releaser/tests/pypirc.txt
zest/releaser/tests/pypirc_both.txt
zest/releaser/tests/pypirc_new.txt
zest/releaser/tests/pypirc_no_input.txt
zest/releaser/tests/pypirc_no_release.txt
zest/releaser/tests/pypirc_old.txt
zest/releaser/tests/pypirc_simple.txt
zest/releaser/tests/pypirc_universal_nocreate.txt
zest/releaser/tests/pypirc_yes_release.txt
zest/releaser/tests/pyproject-toml.txt
zest/releaser/tests/pyproject.toml
zest/releaser/tests/release.txt
zest/releaser/tests/test_setup.py
zest/releaser/tests/utils.txt
zest/releaser/tests/vcs.txt
zest_releaser-9.8.0.dist-info/licenses/LICENSE.GPL
zest_releaser-9.8.0.dist-info/licenses/LICENSE.rst
zest_releaser-9.8.0.dist-info/METADATA
zest_releaser-9.8.0.dist-info/WHEEL
zest_releaser-9.8.0.dist-info/entry_points.txt
zest_releaser-9.8.0.dist-info/top_level.txt
zest_releaser-9.8.0.dist-info/RECORD
