Metadata-Version: 2.4
Name: zest.releaser
Version: 9.8.0
Summary: Software releasing made easy and repeatable
Author-email: Reinout van Rees <reinout@vanrees.org>, Maurits van Rees <maurits@vanrees.org>
License-Expression: GPL-2.0-or-later
Project-URL: documentation, https://zestreleaser.readthedocs.io
Project-URL: repository, https://github.com/zestsoftware/zest.releaser/
Project-URL: changelog, https://github.com/zestsoftware/zest.releaser/blob/master/CHANGES.rst
Keywords: releasing,packaging,pypi
Classifier: Development Status :: 6 - Mature
Classifier: Intended Audience :: Developers
Classifier: Programming Language :: Python
Classifier: Programming Language :: Python :: 3
Classifier: Programming Language :: Python :: 3 :: Only
Classifier: Programming Language :: Python :: 3.9
Classifier: Programming Language :: Python :: 3.10
Classifier: Programming Language :: Python :: 3.11
Classifier: Programming Language :: Python :: 3.12
Classifier: Programming Language :: Python :: 3.13
Classifier: Programming Language :: Python :: 3.14
Classifier: Programming Language :: Python :: Implementation :: CPython
Classifier: Programming Language :: Python :: Implementation :: PyPy
Classifier: Topic :: Software Development :: Libraries :: Python Modules
Requires-Python: >=3.9
License-File: LICENSE.GPL
License-File: LICENSE.rst
Requires-Dist: build>=1.2.0
Requires-Dist: colorama
Requires-Dist: importlib-metadata; python_version < "3.10"
Requires-Dist: packaging
Requires-Dist: readme_renderer[md]>=40
Requires-Dist: requests
Requires-Dist: setuptools>=61.0.0
Requires-Dist: tomli; python_version < "3.11"
Requires-Dist: twine>=1.6.0
Requires-Dist: wheel
Provides-Extra: recommended
Requires-Dist: check-manifest; extra == "recommended"
Requires-Dist: pep440; extra == "recommended"
Requires-Dist: pyroma; extra == "recommended"
Provides-Extra: test
Requires-Dist: zope.testing; extra == "test"
Requires-Dist: zope.testrunner; extra == "test"
Dynamic: license-file
